indicators/__init__.py
indicators/fundindi.py
indicators/techindi.py
signal/__init__.py
signal/handcraft_signal.py
signal/hybrid_signal.py
signal/ml_signal.py
signal/regime_signal.py
unit_test/__init__.py
unit_test/test_indicators.py
unit_test/test_ml_signals.py
unit_test/test_signals.py
alphabuilder_signal-0.2.4.dist-info/METADATA
alphabuilder_signal-0.2.4.dist-info/WHEEL
alphabuilder_signal-0.2.4.dist-info/entry_points.txt
alphabuilder_signal-0.2.4.dist-info/top_level.txt
alphabuilder_signal-0.2.4.dist-info/RECORD
