Metadata-Version: 2.4
Name: alphabuilder_signal
Version: 0.2.4
Summary: Alpha signal library for quantitative finance research
Dynamic: description
Dynamic: description-content-type
Dynamic: summary
